[{
		"filename":	"./ssget_archive/MM/Sandia/fpga_dcop_15/fpga_dcop_15.mtx",
		"problem":	{
			"id":	1069,
			"group":	"Sandia",
			"name":	"fpga_dcop_15",
			"rows":	1220,
			"cols":	1220,
			"nonzeros":	5892,
			"real":	true,
			"binary":	false,
			"2d3d":	false,
			"posdef":	false,
			"psym":	0.81833473507148868,
			"nsym":	0.32211942809083272,
			"kind":	"subsequent circuit simulation problem"
		},
		"spmv":	{
			"csr":	{
				"time":	2.8672000020742416e-05,
				"repetitions":	5
			},
			"csrkokkos":	{
				"time":	6.0415998101234444e-05,
				"repetitions":	5
			},
			"sell":	{
				"time":	1.2697599828243282e-05,
				"repetitions":	5
			}
		}
	}]