[{
		"filename":	"/scratch/hongzhang/ssget_archive/MM/FIDAP/ex5/ex5.mtx",
		"problem":	{
			"id":	436,
			"group":	"FIDAP",
			"name":	"ex5",
			"rows":	27,
			"cols":	27,
			"nonzeros":	279,
			"real":	true,
			"binary":	false,
			"2d3d":	true,
			"posdef":	true,
			"psym":	1,
			"nsym":	1,
			"kind":	"computational fluid dynamics problem"
		},
		"spmv":	{
			"csr":	{
				"time":	1.6179200261831283e-05,
				"repetitions":	5
			},
			"csrkokkos":	{
				"time":	2.78783991932869e-05,
				"repetitions":	5
			}
		}
	}]