[{
		"filename":	"./ssget_archive/MM/Grund/b1_ss/b1_ss.mtx",
		"problem":	{
			"id":	449,
			"group":	"Grund",
			"name":	"b1_ss",
			"rows":	7,
			"cols":	7,
			"nonzeros":	15,
			"real":	true,
			"binary":	false,
			"2d3d":	false,
			"posdef":	false,
			"psym":	0,
			"nsym":	0,
			"kind":	"chemical process simulation problem"
		},
		"spmv":	{
			"csr":	{
				"time":	2.1094399690628052e-05,
				"repetitions":	5
			},
			"csrkokkos":	{
				"time":	4.05503995716572e-05,
				"repetitions":	5
			},
			"sell":	{
				"time":	7.7824001200497274e-06,
				"repetitions":	5
			}
		}
	}]