[
    {
        "filename": "./ssget_archive/MM/Norris/heart2/heart2.mtx",
        "problem": {
            "id": 891,
            "group": "Norris",
            "name": "heart2",
            "rows": 2339,
            "cols": 2339,
            "nonzeros": 682797,
            "real": true,
            "binary": false,
            "2d3d": true,
            "posdef": false,
            "psym": 1,
            "nsym": 0,
            "kind": "2D/3D problem",
            "columns": 2339,
            "row_distribution": {
                "min": 56,
                "q1": 234.0,
                "median": 282.0,
                "q3": 357.0,
                "max": 603,
                "mean": 291.9183411714408,
                "variance": 5721.20709840269,
                "skewness": 0.16888564286213553,
                "kurtosis": 3.2416729435152205,
                "hyperskewness": 2.621927128211051,
                "hyperflatness": 20.68839421803836
            },
            "col_distribution": {
                "min": 56,
                "q1": 234.0,
                "median": 282.0,
                "q3": 357.0,
                "max": 603,
                "mean": 291.9183411714408,
                "variance": 5721.20709840269,
                "skewness": 0.16888564286213553,
                "kurtosis": 3.2416729435152205,
                "hyperskewness": 2.621927128211051,
                "hyperflatness": 20.68839421803836
            }
        },
        "size": 2339,
        "spmv": {
            "csr": {
                "storage": 8230572,
                "max_relative_norm2": 0.7685190054497398,
                "time": 0.000011769600212574004,
                "repetitions": 5,
                "completed": true
            },
            "csri": {
                "storage": 8230572,
                "max_relative_norm2": 1.0000019828925615,
                "time": 0.00001635199971497059,
                "repetitions": 5,
                "completed": true
            },
            "sellp": {
                "completed": false,
                "error": "after determining tmp storage requirements for exclusive_scan: cudaErrorInvalidDeviceFunction: invalid device function"
            }
        },
        "nnz": 682797,
        "optimal": {
            "spmv": "csr"
        }
    }
]
