[{
		"filename":	"./ssget_archive/MM/Newman/polblogs/polblogs.mtx",
		"problem":	{
			"id":	2402,
			"group":	"Newman",
			"name":	"polblogs",
			"rows":	1490,
			"cols":	1490,
			"nonzeros":	19025,
			"real":	true,
			"binary":	false,
			"2d3d":	false,
			"posdef":	false,
			"psym":	0.242561244874356,
			"nsym":	0.24140468930711809,
			"kind":	"directed multigraph"
		},
		"spmv":	{
			"csr":	{
				"time":	2.28608001023531e-05,
				"repetitions":	5
			},
			"csrkokkos":	{
				"time":	0.00010170239806175231,
				"repetitions":	5
			},
			"sell":	{
				"time":	1.1263999901711956e-05,
				"repetitions":	5
			}
		}
	}]