[{
		"filename":	"./ssget_archive/MM/Bai/olm100/olm100.mtx",
		"problem":	{
			"id":	318,
			"group":	"Bai",
			"name":	"olm100",
			"rows":	100,
			"cols":	100,
			"nonzeros":	396,
			"real":	true,
			"binary":	false,
			"2d3d":	true,
			"posdef":	false,
			"psym":	0.668918918918919,
			"nsym":	0.33108108108108109,
			"kind":	"computational fluid dynamics problem"
		},
		"spmv":	{
			"csr":	{
				"time":	2.539519965648651e-05,
				"repetitions":	5
			},
			"csrkokkos":	{
				"time":	5.0176001712679852e-05,
				"repetitions":	5
			},
			"sell":	{
				"time":	1.0035200044512738e-05,
				"repetitions":	5
			}
		}
	}]