[{
		"filename":	"/scratch/hongzhang/ssget_archive/MM/Sandia/fpga_dcop_47/fpga_dcop_47.mtx",
		"problem":	{
			"id":	1101,
			"group":	"Sandia",
			"name":	"fpga_dcop_47",
			"rows":	1220,
			"cols":	1220,
			"nonzeros":	5892,
			"real":	true,
			"binary":	false,
			"2d3d":	false,
			"posdef":	false,
			"psym":	0.81833473507148868,
			"nsym":	0.33179142136248951,
			"kind":	"subsequent circuit simulation problem"
		},
		"spmv":	{
			"csr":	{
				"time":	1.81632000952959e-05,
				"repetitions":	5
			},
			"csrkokkos":	{
				"time":	3.664000034332275e-05,
				"repetitions":	5
			}
		}
	}]