[{
		"filename":	"./ssget_archive/MM/GHS_indef/linverse/linverse.mtx",
		"problem":	{
			"id":	1303,
			"group":	"GHS_indef",
			"name":	"linverse",
			"rows":	11999,
			"cols":	11999,
			"nonzeros":	95977,
			"real":	true,
			"binary":	false,
			"2d3d":	false,
			"posdef":	false,
			"psym":	1,
			"nsym":	1,
			"kind":	"statistical/mathematical problem"
		},
		"spmv":	{
			"csr":	{
				"time":	3.6051200330257412e-05,
				"repetitions":	5
			},
			"csrkokkos":	{
				"time":	0.00014794880151748659,
				"repetitions":	5
			},
			"sell":	{
				"time":	1.5564800053834907e-05,
				"repetitions":	5
			}
		}
	}]