[{
		"filename":	"./ssget_archive/MM/Cote/vibrobox/vibrobox.mtx",
		"problem":	{
			"id":	379,
			"group":	"Cote",
			"name":	"vibrobox",
			"rows":	12328,
			"cols":	12328,
			"nonzeros":	301700,
			"real":	true,
			"binary":	false,
			"2d3d":	true,
			"posdef":	false,
			"psym":	1,
			"nsym":	1,
			"kind":	"acoustics problem"
		},
		"spmv":	{
			"csr":	{
				"time":	3.5750400274991986e-05,
				"repetitions":	5
			},
			"csrkokkos":	{
				"time":	0.000622700798511505,
				"repetitions":	5
			},
			"sell":	{
				"time":	2.1299199759960107e-05,
				"repetitions":	5
			}
		}
	}]